{
  "data": {
    "date": "10/07/2023",
    "resultSet": [
      {
        "failed_dkim": 0
      },
      {
        "total_graymail_recipients": 214162
      },
      {
        "detected_spam": 21458
      },
      {
        "malicious_url": 70
      },
      {
        "total_spoofed_emails": 19611
      },
      {
        "verif_decrypt_success": 5
      },
      {
        "detected_virus": 994
      },
      {
        "threat_content_filter": 8132
      },
      {
        "blocked_invalid_recipient": 126
      },
      {
        "blocked_sdr": 5
      },
      {
        "marketing_mail": 48334
      },
      {
        "ims_spam_increment_over_case": 0
      },
      {
        "total_mailbox_auto_remediated_recipients": 0
      },
      {
        "detected_spam_certain": 17053
      },
      {
        "detected_spam_suspect": 4408
      },
      {
        "blocked_dmarc": 18458
      },
      {
        "total_threat_recipients": 176901
      },
      {
        "total_recipients": 821847
      },
      {
        "verif_decrypt_fail": 0
      },
      {
        "detected_amp": 14
      },
      {
        "bulk_mail": 73488
      },
      {
        "social_mail": 92333
      },
      {
        "total_clean_recipients": 430768
      },
      {
        "detected_virus_per_msg": 125
      },
      {
        "failed_spf": 1148
      },
      {
        "blocked_reputation": 146119
      }
    ],
    "type": "mail_incoming_traffic_summary"
  },
  "meta": {
    "totalCount": 3
  }
}