{
  "data": {
    "date": "29/05/2024",
    "resultSet": [
      {
        "failed_dkim": 2
      },
      {
        "total_graymail_recipients": 214168
      },
      {
        "detected_spam": 21460
      },
      {
        "malicious_url": 77
      },
      {
        "total_spoofed_emails": 19609
      },
      {
        "verif_decrypt_success": 0
      },
      {
        "detected_virus": 993
      },
      {
        "threat_content_filter": 8128
      },
      {
        "blocked_invalid_recipient": 137
      },
      {
        "blocked_sdr": 0
      },
      {
        "marketing_mail": 48352
      },
      {
        "ims_spam_increment_over_case": 0
      },
      {
        "total_mailbox_auto_remediated_recipients": 0
      },
      {
        "detected_spam_certain": 17054
      },
      {
        "detected_spam_suspect": 4411
      },
      {
        "blocked_dmarc": 18463
      },
      {
        "total_threat_recipients": 176899
      },
      {
        "total_recipients": 821847
      },
      {
        "verif_decrypt_fail": 5
      },
      {
        "detected_amp": 24
      },
      {
        "bulk_mail": 73482
      },
      {
        "social_mail": 92339
      },
      {
        "total_clean_recipients": 430783
      },
      {
        "detected_virus_per_msg": 128
      },
      {
        "failed_spf": 1151
      },
      {
        "blocked_reputation": 146111
      }
    ],
    "type": "mail_incoming_traffic_summary"
  },
  "meta": {
    "totalCount": 0
  }
}