{
  "data": {
    "date": "11/02/2024",
    "resultSet": [
      {
        "failed_dkim": 0
      },
      {
        "total_graymail_recipients": 214160
      },
      {
        "detected_spam": 21462
      },
      {
        "malicious_url": 65
      },
      {
        "total_spoofed_emails": 19594
      },
      {
        "verif_decrypt_success": 0
      },
      {
        "detected_virus": 978
      },
      {
        "threat_content_filter": 8114
      },
      {
        "blocked_invalid_recipient": 135
      },
      {
        "blocked_sdr": 3
      },
      {
        "marketing_mail": 48342
      },
      {
        "ims_spam_increment_over_case": 0
      },
      {
        "total_mailbox_auto_remediated_recipients": 0
      },
      {
        "detected_spam_certain": 17045
      },
      {
        "detected_spam_suspect": 4400
      },
      {
        "blocked_dmarc": 18457
      },
      {
        "total_threat_recipients": 176905
      },
      {
        "total_recipients": 821843
      },
      {
        "verif_decrypt_fail": 1
      },
      {
        "detected_amp": 12
      },
      {
        "bulk_mail": 73490
      },
      {
        "social_mail": 92327
      },
      {
        "total_clean_recipients": 430771
      },
      {
        "detected_virus_per_msg": 130
      },
      {
        "failed_spf": 1143
      },
      {
        "blocked_reputation": 146128
      }
    ],
    "type": "mail_incoming_traffic_summary"
  },
  "meta": {
    "totalCount": 0
  }
}