{
  "data": {
    "date": "24/02/2024",
    "resultSet": [
      {
        "detected_virus": 0
      },
      {
        "cres_successful": 0
      },
      {
        "cres_failed": 9
      },
      {
        "threat_content_filter": 7657
      },
      {
        "total_dlp_incidents": 8
      },
      {
        "total_clean_recipients": 170146
      },
      {
        "total_recipients_processed": 177803
      },
      {
        "ims_spam_increment_over_case": 0
      },
      {
        "detected_amp": 8
      },
      {
        "total_recipients": 177931
      },
      {
        "detected_spam": 9
      },
      {
        "total_hard_bounces": 3445
      },
      {
        "detected_virus_per_msg": 11
      },
      {
        "malicious_url": 5
      },
      {
        "total_recipients_delivered": 174483
      }
    ],
    "type": "mail_outgoing_traffic_summary"
  },
  "meta": {
    "totalCount": 4
  }
}