{
  "data": {
    "date": "01/08/2024",
    "resultSet": [
      {
        "detected_virus": 0
      },
      {
        "cres_successful": 0
      },
      {
        "cres_failed": 0
      },
      {
        "threat_content_filter": 7655
      },
      {
        "total_dlp_incidents": 9
      },
      {
        "total_clean_recipients": 170148
      },
      {
        "total_recipients_processed": 177795
      },
      {
        "ims_spam_increment_over_case": 12
      },
      {
        "detected_amp": 20
      },
      {
        "total_recipients": 177919
      },
      {
        "detected_spam": 2
      },
      {
        "total_hard_bounces": 3444
      },
      {
        "detected_virus_per_msg": 0
      },
      {
        "malicious_url": 9
      },
      {
        "total_recipients_delivered": 174489
      }
    ],
    "type": "mail_outgoing_traffic_summary"
  },
  "meta": {
    "totalCount": 11
  }
}