{
  "data": {
    "date": "01/11/2022",
    "resultSet": [
      {
        "failed_dkim": 8
      },
      {
        "total_graymail_recipients": 214162
      },
      {
        "detected_spam": 21447
      },
      {
        "malicious_url": 80
      },
      {
        "total_spoofed_emails": 19600
      },
      {
        "verif_decrypt_success": 8
      },
      {
        "detected_virus": 982
      },
      {
        "threat_content_filter": 8123
      },
      {
        "blocked_invalid_recipient": 112
      },
      {
        "blocked_sdr": 1
      },
      {
        "marketing_mail": 48345
      },
      {
        "ims_spam_increment_over_case": 0
      },
      {
        "total_mailbox_auto_remediated_recipients": 0
      },
      {
        "detected_spam_certain": 17062
      },
      {
        "detected_spam_suspect": 4398
      },
      {
        "blocked_dmarc": 18444
      },
      {
        "total_threat_recipients": 176914
      },
      {
        "total_recipients": 821840
      },
      {
        "verif_decrypt_fail": 0
      },
      {
        "detected_amp": 19
      },
      {
        "bulk_mail": 73470
      },
      {
        "social_mail": 92350
      },
      {
        "total_clean_recipients": 430773
      },
      {
        "detected_virus_per_msg": 134
      },
      {
        "failed_spf": 1149
      },
      {
        "blocked_reputation": 146110
      }
    ],
    "type": "mail_incoming_traffic_summary"
  },
  "meta": {
    "totalCount": 0
  }
}