{
  "data": {
    "date": "28/12/2023",
    "resultSet": [
      {
        "failed_dkim": 0
      },
      {
        "total_graymail_recipients": 214157
      },
      {
        "detected_spam": 21446
      },
      {
        "malicious_url": 62
      },
      {
        "total_spoofed_emails": 19590
      },
      {
        "verif_decrypt_success": 0
      },
      {
        "detected_virus": 988
      },
      {
        "threat_content_filter": 8119
      },
      {
        "blocked_invalid_recipient": 114
      },
      {
        "blocked_sdr": 9
      },
      {
        "marketing_mail": 48328
      },
      {
        "ims_spam_increment_over_case": 2
      },
      {
        "total_mailbox_auto_remediated_recipients": 8
      },
      {
        "detected_spam_certain": 17048
      },
      {
        "detected_spam_suspect": 4408
      },
      {
        "blocked_dmarc": 18460
      },
      {
        "total_threat_recipients": 176900
      },
      {
        "total_recipients": 821857
      },
      {
        "verif_decrypt_fail": 0
      },
      {
        "detected_amp": 30
      },
      {
        "bulk_mail": 73484
      },
      {
        "social_mail": 92349
      },
      {
        "total_clean_recipients": 430768
      },
      {
        "detected_virus_per_msg": 132
      },
      {
        "failed_spf": 1153
      },
      {
        "blocked_reputation": 146130
      }
    ],
    "type": "mail_incoming_traffic_summary"
  },
  "meta": {
    "totalCount": 8
  }
}